hydrotrack/__init__.py
hydrotrack/__main__.py
hydrotrack-1.0.0.dist-info/METADATA
hydrotrack-1.0.0.dist-info/WHEEL
hydrotrack-1.0.0.dist-info/top_level.txt
hydrotrack-1.0.0.dist-info/RECORD
