Metadata-Version: 2.1
Name: hydrotrack
Version: 1.0.0
Summary: A Python package for track and forecasting.
Home-page: https://github.com/hydrotrack-project/hydrotrack
Author: Helvecio B. L. Neto, Alan J. P. Calheiros
Author-email: hydrotrack.project@gmail.com
Classifier: Programming Language :: Python :: 3.10
Classifier: License :: OSI Approved :: MIT License
Classifier: Operating System :: OS Independent
